paaf/agents/__init__.py
paaf/agents/base_agent.py
paaf/agents/multi_agent.py
paaf/agents/chain_of_thought/__init__.py
paaf/agents/chain_of_thought/chain_of_thought_agent.py
paaf/agents/chain_of_thought/chain_of_thought_template.txt
paaf/agents/react/__init__.py
paaf/agents/react/agent.py
paaf/agents/react/react_agent_template.txt
paaf/agents/rewoo/__init__.py
paaf/agents/rewoo/rewoo_agent.py
paaf/agents/rewoo/rewoo_planner_template.txt
paaf/agents/rewoo/rewoo_solver_template.txt
paaf/config/logging.py
paaf/llms/base_llm.py
paaf/llms/openai_llm.py
paaf/models/agent_handoff.py
paaf/models/agent_response.py
paaf/models/multi_agent_architecture.py
paaf/models/shared_models.py
paaf/models/tool.py
paaf/models/react/__init__.py
paaf/models/react/react_agent_response.py
paaf/models/react/react_step_callback.py
paaf/models/rewoo/rewoo_models.py
paaf/models/utils/model_example_json_generator.py
paaf/tools/tool_registory.py
paaf-0.1.8.dist-info/METADATA
paaf-0.1.8.dist-info/WHEEL
paaf-0.1.8.dist-info/RECORD
