Metadata-Version: 2.4
Name: paaf
Version: 0.1.8
Summary: Paaf is an Agent Framework for building AI agents
Keywords: AI agents,agent framework,openai,paaf,pydantic,python-dotenv,requests,wikipedia-api
Requires-Python: >=3.10
Requires-Dist: openai>=1.82.0
Requires-Dist: pydantic>=2.11.5
Requires-Dist: python-dotenv>=1.1.0
Requires-Dist: requests>=2.32.3
Requires-Dist: wikipedia-api>=0.8.1
